esphome_mqtt_timescaledb_ingestor/__init__.py
esphome_mqtt_timescaledb_ingestor/ingestor.py
esphome_mqtt_timescaledb_ingestor-0.3.0.dist-info/entry_points.txt
esphome_mqtt_timescaledb_ingestor-0.3.0.dist-info/LICENSE
esphome_mqtt_timescaledb_ingestor-0.3.0.dist-info/METADATA
esphome_mqtt_timescaledb_ingestor-0.3.0.dist-info/WHEEL
esphome_mqtt_timescaledb_ingestor-0.3.0.dist-info/RECORD
