Metadata-Version: 2.3
Name: esphome-mqtt-timescaledb-ingestor
Version: 0.3.0
Summary: A robust Python service to ingest ESPHome MQTT data into a TimescaleDB multi-table schema.
License: MIT
Keywords: esphome,mqtt,timescaledb,iot,database,ingestor
Author: Ankur Kumar Pandey
Author-email: measure@i-dacs.com
Requires-Python: >=3.7
Classifier: License :: OSI Approved :: MIT License
Classifier: Programming Language :: Python :: 3
Classifier: Programming Language :: Python :: 3.7
Classifier: Programming Language :: Python :: 3.8
Classifier: Programming Language :: Python :: 3.9
Classifier: Programming Language :: Python :: 3.10
Classifier: Programming Language :: Python :: 3.11
Classifier: Programming Language :: Python :: 3.12
Classifier: Programming Language :: Python :: 3.13
Requires-Dist: paho-mqtt (>=1.6.1,<2.0.0)
Requires-Dist: psycopg2-binary (>=2.9.1,<3.0.0)
Requires-Dist: typer[all] (>=0.9.0,<0.10.0)
Project-URL: Homepage, https://i-dacs.com
Project-URL: Repository, https://github.com/paandayankur/mqtt-to-timescaledb-ingester
